sbgm/__init__.py
sbgm/_ode.py
sbgm/_sample.py
sbgm/_shard.py
sbgm/_train.py
sbgm/_utils.py
sbgm/data/__init__.py
sbgm/data/cifar10.py
sbgm/data/flowers.py
sbgm/data/grfs.py
sbgm/data/mnist.py
sbgm/data/moons.py
sbgm/data/quijote.py
sbgm/data/utils.py
sbgm/models/__init__.py
sbgm/models/_dit.py
sbgm/models/_mixer.py
sbgm/models/_mlp.py
sbgm/models/_unet.py
sbgm/sde/__init__.py
sbgm/sde/_sde.py
sbgm/sde/_subvp.py
sbgm/sde/_ve.py
sbgm/sde/_vp.py
sbgm-0.0.38.dist-info/METADATA
sbgm-0.0.38.dist-info/WHEEL
sbgm-0.0.38.dist-info/licenses/LICENSE
sbgm-0.0.38.dist-info/RECORD
