Metadata-Version: 2.4
Name: sbgm
Version: 0.0.38
Summary: Score-based Diffusion models in JAX.
Project-URL: repository, https://github.com/homerjed/sbgm
Author-email: Jed Homer <jedhmr@gmail.com>
License: MIT License
License-File: LICENSE
Keywords: deep-learning,diffusion-models,generative-models,jax,score-based-diffusion
Classifier: Development Status :: 3 - Alpha
Classifier: Intended Audience :: Science/Research
Classifier: License :: OSI Approved :: MIT License
Classifier: Natural Language :: English
Classifier: Programming Language :: Python :: 3
Classifier: Topic :: Scientific/Engineering :: Artificial Intelligence
Requires-Python: ~=3.12
Requires-Dist: beartype==0.19.0
Requires-Dist: cloudpickle==3.0.0
Requires-Dist: diffrax==0.6.0
Requires-Dist: einops>=0.8.0
Requires-Dist: einx==0.3.0
Requires-Dist: equinox==0.11.7
Requires-Dist: jax==0.4.33
Requires-Dist: matplotlib==3.9.1
Requires-Dist: ml-collections==0.1.1
Requires-Dist: numpy==1.26.4
Requires-Dist: optax==0.2.3
Requires-Dist: powerbox==0.8.1
Requires-Dist: scikit-learn==1.5.1
Requires-Dist: torch==2.4.0
Requires-Dist: torchvision==0.19.0
Requires-Dist: tqdm==4.66.4
Provides-Extra: examples
Requires-Dist: datasets; extra == 'examples'
Requires-Dist: matplotlib; extra == 'examples'
Requires-Dist: numpy; extra == 'examples'
